geo_prof/__init__.py
geo_prof/geo_prof.py
geo_prof-0.0.2.dist-info/LICENSE
geo_prof-0.0.2.dist-info/METADATA
geo_prof-0.0.2.dist-info/WHEEL
geo_prof-0.0.2.dist-info/top_level.txt
geo_prof-0.0.2.dist-info/RECORD
