Metadata-Version: 2.1
Name: geo-prof
Version: 0.0.2
Summary: A python package for creating profiles.
Home-page: https://github.com/shakurgds/geo_prof
Author: Shakur
Author-email: shakurgds@gmail.com
License: MIT license
Keywords: geo_prof
Platform: UNKNOWN
Classifier: Development Status :: 2 - Pre-Alpha
Classifier: Intended Audience :: Developers
Classifier: License :: OSI Approved :: MIT License
Classifier: Natural Language :: English
Classifier: Programming Language :: Python :: 3
Classifier: Programming Language :: Python :: 3.5
Classifier: Programming Language :: Python :: 3.6
Classifier: Programming Language :: Python :: 3.7
Classifier: Programming Language :: Python :: 3.8
Requires-Python: >=3.5
